datasetsforecast/__init__.py
datasetsforecast/_modidx.py
datasetsforecast/_nbdev.py
datasetsforecast/favorita.py
datasetsforecast/hierarchical.py
datasetsforecast/long_horizon.py
datasetsforecast/long_horizon2.py
datasetsforecast/m3.py
datasetsforecast/m4.py
datasetsforecast/m5.py
datasetsforecast/phm2008.py
datasetsforecast/utils.py
datasetsforecast-1.0.0.dist-info/LICENSE
datasetsforecast-1.0.0.dist-info/METADATA
datasetsforecast-1.0.0.dist-info/WHEEL
datasetsforecast-1.0.0.dist-info/entry_points.txt
datasetsforecast-1.0.0.dist-info/top_level.txt
datasetsforecast-1.0.0.dist-info/RECORD
