Metadata-Version: 2.1
Name: datasetsforecast
Version: 1.0.0
Summary: Datasets for Time series forecasting
Home-page: https://github.com/Nixtla/datasetsforecast/tree/main/
Author: Nixtla
Author-email: business@nixtla.io
License: MIT License
Keywords: time-series forecasting datasets
Classifier: Development Status :: 3 - Alpha
Classifier: Intended Audience :: Developers
Classifier: Natural Language :: English
Classifier: Programming Language :: Python :: 3.9
Classifier: Programming Language :: Python :: 3.10
Classifier: Programming Language :: Python :: 3.11
Classifier: Programming Language :: Python :: 3.12
Classifier: Programming Language :: Python :: 3.13
Classifier: License :: OSI Approved :: MIT License
Requires-Python: >=3.9
License-File: LICENSE
Requires-Dist: aiohttp
Requires-Dist: numpy
Requires-Dist: scikit-learn
Requires-Dist: pandas
Requires-Dist: requests
Requires-Dist: tqdm
Requires-Dist: utilsforecast>=0.0.8
Requires-Dist: xlrd>=1.0.0
Provides-Extra: dev
Requires-Dist: nbdev==2.3.25; extra == "dev"
Requires-Dist: pre-commit; extra == "dev"
Requires-Dist: setuptools; extra == "dev"
